py_easy_rest_redis_cache/__init__.py
tests/py_easy_rest_redis_cache/__init__.py
tests/py_easy_rest_redis_cache/test_redis_cache.py
py_easy_rest_redis_cache-0.1.3.dist-info/METADATA
py_easy_rest_redis_cache-0.1.3.dist-info/WHEEL
py_easy_rest_redis_cache-0.1.3.dist-info/top_level.txt
py_easy_rest_redis_cache-0.1.3.dist-info/RECORD
