Metadata-Version: 2.1
Name: py-easy-rest-redis-cache
Version: 0.1.3
Summary: Redis cache to use with Py Easy REST
Author: Jean Pinzon
Author-email: jean.pinzon1@gmail.com
Classifier: Programming Language :: Python :: 3
Classifier: License :: OSI Approved :: MIT License
Classifier: Operating System :: OS Independent
Requires-Python: >=3.8
Requires-Dist: aioredis (==1.3.1)
Provides-Extra: tests
Requires-Dist: pytest (==7.1.2) ; extra == 'tests'
Requires-Dist: pytest-asyncio (==0.14.0) ; extra == 'tests'
Requires-Dist: pytest-cov (==2.10.1) ; extra == 'tests'
Requires-Dist: flake8 (==3.8.4) ; extra == 'tests'
Requires-Dist: aiounittest (==1.4.0) ; extra == 'tests'
Requires-Dist: twine (==3.3.0) ; extra == 'tests'
Requires-Dist: build (==0.3.1.post1) ; extra == 'tests'
